00_digital_hardware/controller_logic/src/original/fulladd.vhd
----------------------------------------------------------------------------------
-- Company: 
-- Engineer: 
-- 
-- Create Date: 2024/10/24 22:24:48
-- Design Name: 
-- Module Name: fulladd - Behavioral
-- Project Name: 
-- Target Devices: 
-- Tool Versions: 
-- Description: 
-- 
-- Dependencies: 
-- 
-- Revision:
-- Revision 0.01 - File Created
-- Additional Comments:
-- 
----------------------------------------------------------------------------------


library IEEE;
use IEEE.STD_LOGIC_1164.ALL;

-- Uncomment the following library declaration if using
-- arithmetic functions with Signed or Unsigned values
--use IEEE.NUMERIC_STD.ALL;

-- Uncomment the following library declaration if instantiating
-- any Xilinx leaf cells in this code.
--library UNISIM;
--use UNISIM.VComponents.all;

entity fulladd is
    Port ( a : in STD_LOGIC;
           b : in STD_LOGIC;
           cin : in STD_LOGIC;
           s : out STD_LOGIC;
           cout : out STD_LOGIC);
end fulladd;

architecture Behavioral of fulladd is
        
        signal t1, t2, t3 : STD_LOGIC ; 
begin

    t1 <= a xor b;
    t2 <= a and b; 
    t3 <= t1 and cin;
    s <= t1 xor cin;
    cout <= t2 or t3; 

end Behavioral;

00_digital_hardware/controller_logic/tb/original_archive/fulladd_tb.vhd
library IEEE;
use IEEE.STD_LOGIC_1164.ALL;

entity fulladd_tb is
end fulladd_tb;

architecture Behavioral of fulladd_tb is
    component fulladd is
        Port ( a : in STD_LOGIC;
               b : in STD_LOGIC;
               cin : in STD_LOGIC;
               s : out STD_LOGIC;
               cout : out STD_LOGIC);
    end component;
    signal a, b, cin, s, cout : std_logic;
begin
    UUT: fulladd port map (a=>a, b=>b, cin=>cin, s=>s, cout=>cout);
    process
    begin
        a <= '0'; b <= '0'; cin <= '0'; wait for 20 ns;
        a <= '0'; b <= '0'; cin <= '1'; wait for 20 ns;
        a <= '0'; b <= '1'; cin <= '0'; wait for 20 ns;
        a <= '0'; b <= '1'; cin <= '1'; wait for 20 ns;
        a <= '1'; b <= '0'; cin <= '0'; wait for 20 ns;
        a <= '1'; b <= '0'; cin <= '1'; wait for 20 ns;
        a <= '1'; b <= '1'; cin <= '0'; wait for 20 ns;
        a <= '1'; b <= '1'; cin <= '1'; wait;
    end process;
end Behavioral;

00_digital_hardware/controller_logic/results/vcd/original_fulladd_tb.vcd
$date
  Thu Jul 30 00:29:07 2026
$end
$version
  GHDL v0
$end
$timescale
  1 fs
$end
$scope module standard $end
$upscope $end
$scope module textio $end
$upscope $end
$scope module std_logic_1164 $end
$upscope $end
$scope module fulladd_tb $end
$var reg 1 ! a $end
$var reg 1 " b $end
$var reg 1 # cin $end
$var reg 1 $ s $end
$var reg 1 % cout $end
$scope module uut $end
$var reg 1 & a $end
$var reg 1 ' b $end
$var reg 1 ( cin $end
$var reg 1 ) s $end
$var reg 1 * cout $end
$var reg 1 + t1 $end
$var reg 1 , t2 $end
$var reg 1 - t3 $end
$upscope $end
$upscope $end
$enddefinitions $end
#0
0!
0"
0#
0$
0%
0&
0'
0(
0)
0*
0+
0,
0-
#20000000
1#
1$
1(
1)
#40000000
1"
0#
1$
1'
0(
1)
1+
#60000000
1#
0$
1%
1(
0)
1*
1-
#80000000
1!
0"
0#
1$
0%
1&
0'
0(
1)
0*
0-
#100000000
1#
0$
1%
1(
0)
1*
1-
#120000000
1"
0#
0$
1'
0(
0)
0+
1,
0-
#140000000
1#
1$
1(
1)
