00_digital_hardware/controller_logic/src/original/mealy_101.vhd
----------------------------------------------------------------------------------
-- Company: 
-- Engineer: 
-- 
-- Create Date: 2024/11/22 16:00:10
-- Design Name: 
-- Module Name: mealy - Behavioral
-- Project Name: 
-- Target Devices: 
-- Tool Versions: 
-- Description: 
-- 
-- Dependencies: 
-- 
-- Revision:
-- Revision 0.01 - File Created
-- Additional Comments:
-- 
----------------------------------------------------------------------------------


library IEEE;
use IEEE.STD_LOGIC_1164.ALL;

-- Uncomment the following library declaration if using
-- arithmetic functions with Signed or Unsigned values
--use IEEE.NUMERIC_STD.ALL;

-- Uncomment the following library declaration if instantiating
-- any Xilinx leaf cells in this code.
--library UNISIM;
--use UNISIM.VComponents.all;

entity mealy is
    Port ( clk : in STD_LOGIC;
           din : in STD_LOGIC;
           rst : in STD_LOGIC;
           dout : out STD_LOGIC);
end mealy;

architecture Behavioral of mealy is
    type state is (st0, st1, st2, st3);
    signal present_state, next_state : state;
begin
    syncronous_process : process (clk)
    begin
        if rising_edge(clk) then
            if (rst = '1') then
                present_state <= st0;
            else
                present_state <= next_state;
            end if;
        end if;
    end process;
    
    next_state_and_output_decoder :       
    process(present_state, din)
    begin
        case (present_state) is 
            when st0 =>
                     if (din = '1') then
                            next_state <= st1;
                            dout <= '0';
                    else
                            next_state <= st0;
                            dout <= '0';
                    end if;
            
            when St1 =>
                   if (din = '0') then
                            next_state <= st2;
                            dout <= '0';
                   else
                            next_state <= st1;
                            dout <= '0';
                   end if;
            
            when St2 =>
                   if (din = '1') then
                            next_state <= st1;
                            dout <= '1';
                   else
                            next_state <= st2;
                            dout <= '0';
                   end if;            
            
            when others =>
                   next_state <= st0;
                   dout <= '0';
        end case;
    end process;
end Behavioral;

00_digital_hardware/controller_logic/tb/original_archive/mealy_tb.vhd
library IEEE;
use IEEE.STD_LOGIC_1164.ALL;

entity mealy_tb is
end mealy_tb;

architecture Behavioral of mealy_tb is
    component mealy
        port(
          clk : in std_logic;
          din : in std_logic;
          rst : in std_logic;
          dout : out std_logic
        );
    end component;
    signal clk : std_logic := '0';
    signal din : std_logic := '0';
    signal rst : std_logic := '0';
    signal dout : std_logic;
    constant clk_period : time := 20 ns;
begin
    UUT: mealy port map (clk => clk, din => din, rst => rst, dout => dout);
    clk_process: process
    begin
        clk <= '0'; wait for clk_period/2;
        clk <= '1'; wait for clk_period/2;
    end process;
    stim_proc: process
    begin
        rst <= '1'; wait for 100 ns;
        rst <= '0'; din <= '0'; wait for 20 ns;
        din <= '1'; wait for 20 ns;
        din <= '0'; wait for 20 ns;
        din <= '1'; wait for 20 ns;
        din <= '0'; wait for 20 ns;
        din <= '1'; wait for 20 ns;
        din <= '0'; wait for 20 ns;
        din <= '1';
        wait;
    end process;
end Behavioral;

00_digital_hardware/controller_logic/results/vcd/original_mealy_tb.vcd
$date
  Thu Jul 30 00:29:07 2026
$end
$version
  GHDL v0
$end
$timescale
  1 fs
$end
$scope module standard $end
$upscope $end
$scope module textio $end
$upscope $end
$scope module std_logic_1164 $end
$upscope $end
$scope module mealy_tb $end
$var reg 1 ! clk $end
$var reg 1 " din $end
$var reg 1 # rst $end
$var reg 1 $ dout $end
$scope module uut $end
$var reg 1 % clk $end
$var reg 1 & din $end
$var reg 1 ' rst $end
$var reg 1 ( dout $end
$comment present_state is not handled $end
$comment next_state is not handled $end
$upscope $end
$upscope $end
$enddefinitions $end
#0
0!
0"
1#
0$
0%
0&
1'
0(
#10000000
1!
1%
#20000000
0!
0%
#30000000
1!
1%
#40000000
0!
0%
#50000000
1!
1%
#60000000
0!
0%
#70000000
1!
1%
#80000000
0!
0%
#90000000
1!
1%
#100000000
0!
0#
0%
0'
#110000000
1!
1%
#120000000
0!
1"
0%
1&
#130000000
1!
1%
#140000000
0!
0"
0%
0&
#150000000
1!
1%
#160000000
0!
1"
1$
0%
1&
1(
#170000000
1!
0$
1%
0(
#180000000
0!
0"
0%
0&
#190000000
1!
1%
#200000000
0!
1"
1$
0%
1&
1(
#210000000
1!
0$
1%
0(
#220000000
0!
0"
0%
0&
#230000000
1!
1%
#240000000
0!
1"
1$
0%
1&
1(
#250000000
1!
0$
1%
0(
