00_digital_hardware/controller_logic/src/original/fulladd.vhd
----------------------------------------------------------------------------------
-- Company: 
-- Engineer: 
-- 
-- Create Date: 2024/10/24 22:24:48
-- Design Name: 
-- Module Name: fulladd - Behavioral
-- Project Name: 
-- Target Devices: 
-- Tool Versions: 
-- Description: 
-- 
-- Dependencies: 
-- 
-- Revision:
-- Revision 0.01 - File Created
-- Additional Comments:
-- 
----------------------------------------------------------------------------------


library IEEE;
use IEEE.STD_LOGIC_1164.ALL;

-- Uncomment the following library declaration if using
-- arithmetic functions with Signed or Unsigned values
--use IEEE.NUMERIC_STD.ALL;

-- Uncomment the following library declaration if instantiating
-- any Xilinx leaf cells in this code.
--library UNISIM;
--use UNISIM.VComponents.all;

entity fulladd is
    Port ( a : in STD_LOGIC;
           b : in STD_LOGIC;
           cin : in STD_LOGIC;
           s : out STD_LOGIC;
           cout : out STD_LOGIC);
end fulladd;

architecture Behavioral of fulladd is
        
        signal t1, t2, t3 : STD_LOGIC ; 
begin

    t1 <= a xor b;
    t2 <= a and b; 
    t3 <= t1 and cin;
    s <= t1 xor cin;
    cout <= t2 or t3; 

end Behavioral;

00_digital_hardware/controller_logic/src/original/add_4bits.vhd
----------------------------------------------------------------------------------
-- Company: 
-- Engineer: 
-- 
-- Create Date: 2024/10/24 22:30:44
-- Design Name: 
-- Module Name: add_4bits - Behavioral
-- Project Name: 
-- Target Devices: 
-- Tool Versions: 
-- Description: 
-- 
-- Dependencies: 
-- 
-- Revision:
-- Revision 0.01 - File Created
-- Additional Comments:
-- 
----------------------------------------------------------------------------------


library IEEE;
use IEEE.STD_LOGIC_1164.ALL;

-- Uncomment the following library declaration if using
-- arithmetic functions with Signed or Unsigned values
--use IEEE.NUMERIC_STD.ALL;

-- Uncomment the following library declaration if instantiating
-- any Xilinx leaf cells in this code.
--library UNISIM;
--use UNISIM.VComponents.all;

entity add_4bits is
    Port ( a : in STD_LOGIC_VECTOR (3 downto 0);
           b : in STD_LOGIC_VECTOR (3 downto 0);
           cin : in STD_LOGIC;
           sum : out STD_LOGIC_VECTOR (3 downto 0);
           cout : out STD_LOGIC);
end add_4bits;

architecture Behavioral of add_4bits is
    component fulladd
        Port ( a, b, cin : in STD_LOGIC;
               s, cout : out STD_LOGIC);
        end component;
    
    signal tcout1, tcout2, tcout3 : std_logic;
    
begin
    U1: fulladd port map (a(0), b(0), cin, sum(0), tcout1);
    U2: fulladd port map (a(1), b(1), tcout1, sum(1), tcout2);
    U3: fulladd port map (a(2), b(2), tcout2, sum(2), tcout3);
    U4: fulladd port map (a(3), b(3), tcout3, sum(3), cout);

end Behavioral;

00_digital_hardware/controller_logic/tb/tb_add_4bits.vhd
library ieee;
use ieee.std_logic_1164.all;
use ieee.numeric_std.all;
use std.env.all;

entity tb_add_4bits is end;
architecture test of tb_add_4bits is
  signal a, b, sum : std_logic_vector(3 downto 0);
  signal cin, cout : std_logic;
begin
  dut : entity work.add_4bits port map (a, b, cin, sum, cout);
  process
    variable total : integer;
  begin
    for av in 0 to 15 loop
      for bv in 0 to 15 loop
        for cv in 0 to 1 loop
          a <= std_logic_vector(to_unsigned(av, 4));
          b <= std_logic_vector(to_unsigned(bv, 4));
          if cv = 0 then cin <= '0'; else cin <= '1'; end if;
          wait for 1 ns;
          total := av + bv + cv;
          assert unsigned(sum) = to_unsigned(total mod 16, 4) severity failure;
          if total >= 16 then
            assert cout = '1' severity failure;
          else
            assert cout = '0' severity failure;
          end if;
        end loop;
      end loop;
    end loop;
    report "PASS tb_add_4bits";
    stop;
    wait;
  end process;
end;

00_digital_hardware/controller_logic/results/vcd/tb_add_4bits.vcd
$date
  Thu Jul 30 00:29:07 2026
$end
$version
  GHDL v0
$end
$timescale
  1 fs
$end
$scope module standard $end
$upscope $end
$scope module textio $end
$upscope $end
$scope module std_logic_1164 $end
$upscope $end
$scope module numeric_std $end
$upscope $end
$scope module env $end
$upscope $end
$scope module tb_add_4bits $end
$var reg 4 ! a[3:0] $end
$var reg 4 " b[3:0] $end
$var reg 4 # sum[3:0] $end
$var reg 1 $ cin $end
$var reg 1 % cout $end
$scope module dut $end
$var reg 4 & a[3:0] $end
$var reg 4 ' b[3:0] $end
$var reg 1 ( cin $end
$var reg 4 ) sum[3:0] $end
$var reg 1 * cout $end
$var reg 1 + tcout1 $end
$var reg 1 , tcout2 $end
$var reg 1 - tcout3 $end
$scope module u1 $end
$var reg 1 . a $end
$var reg 1 / b $end
$var reg 1 0 cin $end
$var reg 1 1 s $end
$var reg 1 2 cout $end
$var reg 1 3 t1 $end
$var reg 1 4 t2 $end
$var reg 1 5 t3 $end
$upscope $end
$scope module u2 $end
$var reg 1 6 a $end
$var reg 1 7 b $end
$var reg 1 8 cin $end
$var reg 1 9 s $end
$var reg 1 : cout $end
$var reg 1 ; t1 $end
$var reg 1 < t2 $end
$var reg 1 = t3 $end
$upscope $end
$scope module u3 $end
$var reg 1 > a $end
$var reg 1 ? b $end
$var reg 1 @ cin $end
$var reg 1 A s $end
$var reg 1 B cout $end
$var reg 1 C t1 $end
$var reg 1 D t2 $end
$var reg 1 E t3 $end
$upscope $end
$scope module u4 $end
$var reg 1 F a $end
$var reg 1 G b $end
$var reg 1 H cin $end
$var reg 1 I s $end
$var reg 1 J cout $end
$var reg 1 K t1 $end
$var reg 1 L t2 $end
$var reg 1 M t3 $end
$upscope $end
$upscope $end
$upscope $end
$enddefinitions $end
#0
b0000 !
b0000 "
b0000 #
0$
0%
b0000 &
b0000 '
0(
b0000 )
0*
0+
0,
0-
0.
0/
00
01
02
03
04
05
06
07
08
09
0:
0;
0<
0=
0>
0?
0@
0A
0B
0C
0D
0E
0F
0G
0H
0I
0J
0K
0L
0M
#1000000
b0001 #
1$
1(
b0001 )
10
11
#2000000
b0001 "
b0001 #
0$
b0001 '
0(
b0001 )
1/
00
11
13
#3000000
b0010 #
1$
1(
b0010 )
1+
10
01
12
15
18
19
#4000000
b0010 "
b0010 #
0$
b0010 '
0(
b0010 )
0+
0,
0/
00
01
02
03
05
17
08
19
0:
1;
0=
0@
0A
#5000000
b0011 #
1$
1(
b0011 )
10
11
#6000000
b0011 "
b0011 #
0$
b0011 '
0(
b0011 )
1/
00
11
13
#7000000
b0100 #
1$
1(
b0100 )
1+
1,
10
01
12
15
18
09
1:
1=
1@
1A
#8000000
b0100 "
b0100 #
0$
b0100 '
0(
b0100 )
0+
0,
0-
0/
00
01
02
03
05
07
08
09
0:
0;
0=
1?
0@
1A
0B
1C
0E
0H
0I
#9000000
b0101 #
1$
1(
b0101 )
10
11
#10000000
b0101 "
b0101 #
0$
b0101 '
0(
b0101 )
1/
00
11
13
#11000000
b0110 #
1$
1(
b0110 )
1+
10
01
12
15
18
19
#12000000
b0110 "
b0110 #
0$
b0110 '
0(
b0110 )
0+
0,
0-
0/
00
01
02
03
05
17
08
19
0:
1;
0=
0@
1A
0B
0E
0H
0I
#13000000
b0111 #
1$
1(
b0111 )
10
11
#14000000
b0111 "
b0111 #
0$
b0111 '
0(
b0111 )
1/
00
11
13
#15000000
b1000 #
1$
1(
b1000 )
1+
1,
1-
10
01
12
15
18
09
1:
1=
1@
0A
1B
1E
1H
1I
#16000000
b1000 "
b1000 #
0$
0%
b1000 '
0(
b1000 )
0*
0+
0,
0-
0/
00
01
02
03
05
07
08
09
0:
0;
0=
0?
0@
0A
0B
0C
0E
1G
0H
1I
0J
1K
0M
#17000000
b1001 #
1$
1(
b1001 )
10
11
#18000000
b1001 "
b1001 #
0$
b1001 '
0(
b1001 )
1/
00
11
13
#19000000
b1010 #
1$
1(
b1010 )
1+
10
01
12
15
18
19
#20000000
b1010 "
b1010 #
0$
b1010 '
0(
b1010 )
0+
0,
0/
00
01
02
03
05
17
08
19
0:
1;
0=
0@
0A
#21000000
b1011 #
1$
1(
b1011 )
10
11
#22000000
b1011 "
b1011 #
0$
b1011 '
0(
b1011 )
1/
00
11
13
#23000000
b1100 #
1$
1(
b1100 )
1+
1,
10
01
12
15
18
09
1:
1=
1@
1A
#24000000
b1100 "
b1100 #
0$
0%
b1100 '
0(
b1100 )
0*
0+
0,
0-
0/
00
01
02
03
05
07
08
09
0:
0;
0=
1?
0@
1A
0B
1C
0E
0H
1I
0J
0M
#25000000
b1101 #
1$
1(
b1101 )
10
11
#26000000
b1101 "
b1101 #
0$
b1101 '
0(
b1101 )
1/
00
11
13
#27000000
b1110 #
1$
1(
b1110 )
1+
10
01
12
15
18
19
#28000000
b1110 "
b1110 #
0$
0%
b1110 '
0(
b1110 )
0*
0+
0,
0-
0/
00
01
02
03
05
17
08
19
0:
1;
0=
0@
1A
0B
0E
0H
1I
0J
0M
#29000000
b1111 #
1$
1(
b1111 )
10
11
#30000000
b1111 "
b1111 #
0$
b1111 '
0(
b1111 )
1/
00
11
13
#31000000
b0000 #
1$
1%
1(
b0000 )
1*
1+
1,
1-
10
01
12
15
18
09
1:
1=
1@
0A
1B
1E
1H
0I
1J
1M
#32000000
b0001 !
b0000 "
b0001 #
0$
0%
b0001 &
b0000 '
0(
b0001 )
0*
0+
0,
0-
1.
0/
00
11
02
05
07
08
09
0:
0;
0=
0?
0@
0A
0B
0C
0E
0G
0H
0I
0J
0K
0M
#33000000
b0010 #
1$
1(
b0010 )
1+
10
01
12
15
18
19
#34000000
b0001 "
b0010 #
0$
b0001 '
0(
b0010 )
1/
00
01
03
14
05
#35000000
b0011 #
1$
1(
b0011 )
10
11
#36000000
b0010 "
b0011 #
0$
b0010 '
0(
b0011 )
0+
0,
0/
00
11
02
13
04
17
08
19
0:
1;
0=
0@
0A
#37000000
b0100 #
1$
1(
b0100 )
1+
1,
10
01
12
15
18
09
1:
1=
1@
1A
#38000000
b0011 "
b0100 #
0$
b0011 '
0(
b0100 )
1/
00
01
03
14
05
#39000000
b0101 #
1$
1(
b0101 )
10
11
#40000000
b0100 "
b0101 #
0$
b0100 '
0(
b0101 )
0+
0,
0-
0/
00
11
02
13
04
07
08
09
0:
0;
0=
1?
0@
1A
0B
1C
0E
0H
0I
#41000000
b0110 #
1$
1(
b0110 )
1+
10
01
12
15
18
19
#42000000
b0101 "
b0110 #
0$
b0101 '
0(
b0110 )
1/
00
01
03
14
05
#43000000
b0111 #
1$
1(
b0111 )
10
11
#44000000
b0110 "
b0111 #
0$
b0110 '
0(
b0111 )
0+
0,
0-
0/
00
11
02
13
04
17
08
19
0:
1;
0=
0@
1A
0B
0E
0H
0I
#45000000
b1000 #
1$
1(
b1000 )
1+
1,
1-
10
01
12
15
18
09
1:
1=
1@
0A
1B
1E
1H
1I
#46000000
b0111 "
b1000 #
0$
b0111 '
0(
b1000 )
1/
00
01
03
14
05
#47000000
b1001 #
1$
1(
b1001 )
10
11
#48000000
b1000 "
b1001 #
0$
0%
b1000 '
0(
b1001 )
0*
0+
0,
0-
0/
00
11
02
13
04
07
08
09
0:
0;
0=
0?
0@
0A
0B
0C
0E
1G
0H
1I
0J
1K
0M
#49000000
b1010 #
1$
1(
b1010 )
1+
10
01
12
15
18
19
#50000000
b1001 "
b1010 #
0$
b1001 '
0(
b1010 )
1/
00
01
03
14
05
#51000000
b1011 #
1$
1(
b1011 )
10
11
#52000000
b1010 "
b1011 #
0$
b1010 '
0(
b1011 )
0+
0,
0/
00
11
02
13
04
17
08
19
0:
1;
0=
0@
0A
#53000000
b1100 #
1$
1(
b1100 )
1+
1,
10
01
12
15
18
09
1:
1=
1@
1A
#54000000
b1011 "
b1100 #
0$
b1011 '
0(
b1100 )
1/
00
01
03
14
05
#55000000
b1101 #
1$
1(
b1101 )
10
11
#56000000
b1100 "
b1101 #
0$
0%
b1100 '
0(
b1101 )
0*
0+
0,
0-
0/
00
11
02
13
04
07
08
09
0:
0;
0=
1?
0@
1A
0B
1C
0E
0H
1I
0J
0M
#57000000
b1110 #
1$
1(
b1110 )
1+
10
01
12
15
18
19
#58000000
b1101 "
b1110 #
0$
b1101 '
0(
b1110 )
1/
00
01
03
14
05
#59000000
b1111 #
1$
1(
b1111 )
10
11
#60000000
b1110 "
b1111 #
0$
0%
b1110 '
0(
b1111 )
0*
0+
0,
0-
0/
00
11
02
13
04
17
08
19
0:
1;
0=
0@
1A
0B
0E
0H
1I
0J
0M
#61000000
b0000 #
1$
1%
1(
b0000 )
1*
1+
1,
1-
10
01
12
15
18
09
1:
1=
1@
0A
1B
1E
1H
0I
1J
1M
#62000000
b1111 "
b0000 #
0$
b1111 '
0(
b0000 )
1/
00
01
03
14
05
#63000000
b0001 #
1$
1(
b0001 )
10
11
#64000000
b0010 !
b0000 "
b0010 #
0$
0%
b0010 &
b0000 '
0(
b0010 )
0*
0+
0,
0-
0.
0/
00
01
02
04
16
07
08
19
0:
0=
0?
0@
0A
0B
0C
0E
0G
0H
0I
0J
0K
0M
#65000000
b0011 #
1$
1(
b0011 )
10
11
#66000000
b0001 "
b0011 #
0$
b0001 '
0(
b0011 )
1/
00
11
13
#67000000
b0100 #
1$
1(
b0100 )
1+
1,
10
01
12
15
18
09
1:
1=
1@
1A
#68000000
b0010 "
b0100 #
0$
b0010 '
0(
b0100 )
0+
0/
00
01
02
03
05
17
08
09
0;
1<
0=
#69000000
b0101 #
1$
1(
b0101 )
10
11
#70000000
b0011 "
b0101 #
0$
b0011 '
0(
b0101 )
1/
00
11
13
#71000000
b0110 #
1$
1(
b0110 )
1+
10
01
12
15
18
19
#72000000
b0100 "
b0110 #
0$
b0100 '
0(
b0110 )
0+
0,
0-
0/
00
01
02
03
05
07
08
19
0:
1;
0<
0=
1?
0@
1A
0B
1C
0E
0H
0I
#73000000
b0111 #
1$
1(
b0111 )
10
11
#74000000
b0101 "
b0111 #
0$
b0101 '
0(
b0111 )
1/
00
11
13
#75000000
b1000 #
1$
1(
b1000 )
1+
1,
1-
10
01
12
15
18
09
1:
1=
1@
0A
1B
1E
1H
1I
#76000000
b0110 "
b1000 #
0$
b0110 '
0(
b1000 )
0+
0/
00
01
02
03
05
17
08
09
0;
1<
0=
#77000000
b1001 #
1$
1(
b1001 )
10
11
#78000000
b0111 "
b1001 #
0$
b0111 '
0(
b1001 )
1/
00
11
13
#79000000
b1010 #
1$
1(
b1010 )
1+
10
01
12
15
18
19
#80000000
b1000 "
b1010 #
0$
0%
b1000 '
0(
b1010 )
0*
0+
0,
0-
0/
00
01
02
03
05
07
08
19
0:
1;
0<
0=
0?
0@
0A
0B
0C
0E
1G
0H
1I
0J
1K
0M
#81000000
b1011 #
1$
1(
b1011 )
10
11
#82000000
b1001 "
b1011 #
0$
b1001 '
0(
b1011 )
1/
00
11
13
#83000000
b1100 #
1$
1(
b1100 )
1+
1,
10
01
12
15
18
09
1:
1=
1@
1A
#84000000
b1010 "
b1100 #
0$
b1010 '
0(
b1100 )
0+
0/
00
01
02
03
05
17
08
09
0;
1<
0=
#85000000
b1101 #
1$
1(
b1101 )
10
11
#86000000
b1011 "
b1101 #
0$
b1011 '
0(
b1101 )
1/
00
11
13
#87000000
b1110 #
1$
1(
b1110 )
1+
10
01
12
15
18
19
#88000000
b1100 "
b1110 #
0$
0%
b1100 '
0(
b1110 )
0*
0+
0,
0-
0/
00
01
02
03
05
07
08
19
0:
1;
0<
0=
1?
0@
1A
0B
1C
0E
0H
1I
0J
0M
#89000000
b1111 #
1$
1(
b1111 )
10
11
#90000000
b1101 "
b1111 #
0$
b1101 '
0(
b1111 )
1/
00
11
13
#91000000
b0000 #
1$
1%
1(
b0000 )
1*
1+
1,
1-
10
01
12
15
18
09
1:
1=
1@
0A
1B
1E
1H
0I
1J
1M
#92000000
b1110 "
b0000 #
0$
b1110 '
0(
b0000 )
0+
0/
00
01
02
03
05
17
08
09
0;
1<
0=
#93000000
b0001 #
1$
1(
b0001 )
10
11
#94000000
b1111 "
b0001 #
0$
b1111 '
0(
b0001 )
1/
00
11
13
#95000000
b0010 #
1$
1(
b0010 )
1+
10
01
12
15
18
19
#96000000
b0011 !
b0000 "
b0011 #
0$
0%
b0011 &
b0000 '
0(
b0011 )
0*
0+
0,
0-
1.
0/
00
11
02
05
07
08
19
0:
1;
0<
0=
0?
0@
0A
0B
0C
0E
0G
0H
0I
0J
0K
0M
#97000000
b0100 #
1$
1(
b0100 )
1+
1,
10
01
12
15
18
09
1:
1=
1@
1A
#98000000
b0001 "
b0100 #
0$
b0001 '
0(
b0100 )
1/
00
01
03
14
05
#99000000
b0101 #
1$
1(
b0101 )
10
11
#100000000
b0010 "
b0101 #
0$
b0010 '
0(
b0101 )
0+
0/
00
11
02
13
04
17
08
09
0;
1<
0=
#101000000
b0110 #
1$
1(
b0110 )
1+
10
01
12
15
18
19
#102000000
b0011 "
b0110 #
0$
b0011 '
0(
b0110 )
1/
00
01
03
14
05
#103000000
b0111 #
1$
1(
b0111 )
10
11
#104000000
b0100 "
b0111 #
0$
b0100 '
0(
b0111 )
0+
0,
0-
0/
00
11
02
13
04
07
08
19
0:
1;
0<
0=
1?
0@
1A
0B
1C
0E
0H
0I
#105000000
b1000 #
1$
1(
b1000 )
1+
1,
1-
10
01
12
15
18
09
1:
1=
1@
0A
1B
1E
1H
1I
#106000000
b0101 "
b1000 #
0$
b0101 '
0(
b1000 )
1/
00
01
03
14
05
#107000000
b1001 #
1$
1(
b1001 )
10
11
#108000000
b0110 "
b1001 #
0$
b0110 '
0(
b1001 )
0+
0/
00
11
02
13
04
17
08
09
0;
1<
0=
#109000000
b1010 #
1$
1(
b1010 )
1+
10
01
12
15
18
19
#110000000
b0111 "
b1010 #
0$
b0111 '
0(
b1010 )
1/
00
01
03
14
05
#111000000
b1011 #
1$
1(
b1011 )
10
11
#112000000
b1000 "
b1011 #
0$
0%
b1000 '
0(
b1011 )
0*
0+
0,
0-
0/
00
11
02
13
04
07
08
19
0:
1;
0<
0=
0?
0@
0A
0B
0C
0E
1G
0H
1I
0J
1K
0M
#113000000
b1100 #
1$
1(
b1100 )
1+
1,
10
01
12
15
18
09
1:
1=
1@
1A
#114000000
b1001 "
b1100 #
0$
b1001 '
0(
b1100 )
1/
00
01
03
14
05
#115000000
b1101 #
1$
1(
b1101 )
10
11
#116000000
b1010 "
b1101 #
0$
b1010 '
0(
b1101 )
0+
0/
00
11
02
13
04
17
08
09
0;
1<
0=
#117000000
b1110 #
1$
1(
b1110 )
1+
10
01
12
15
18
19
#118000000
b1011 "
b1110 #
0$
b1011 '
0(
b1110 )
1/
00
01
03
14
05
#119000000
b1111 #
1$
1(
b1111 )
10
11
#120000000
b1100 "
b1111 #
0$
0%
b1100 '
0(
b1111 )
0*
0+
0,
0-
0/
00
11
02
13
04
07
08
19
0:
1;
0<
0=
1?
0@
1A
0B
1C
0E
0H
1I
0J
0M
#121000000
b0000 #
1$
1%
1(
b0000 )
1*
1+
1,
1-
10
01
12
15
18
09
1:
1=
1@
0A
1B
1E
1H
0I
1J
1M
#122000000
b1101 "
b0000 #
0$
b1101 '
0(
b0000 )
1/
00
01
03
14
05
#123000000
b0001 #
1$
1(
b0001 )
10
11
#124000000
b1110 "
b0001 #
0$
b1110 '
0(
b0001 )
0+
0/
00
11
02
13
04
17
08
09
0;
1<
0=
#125000000
b0010 #
1$
1(
b0010 )
1+
10
01
12
15
18
19
#126000000
b1111 "
b0010 #
0$
b1111 '
0(
b0010 )
1/
00
01
03
14
05
#127000000
b0011 #
1$
1(
b0011 )
10
11
#128000000
b0100 !
b0000 "
b0100 #
0$
0%
b0100 &
b0000 '
0(
b0100 )
0*
0+
0,
0-
0.
0/
00
01
02
04
06
07
08
09
0:
0<
1>
0?
0@
1A
0B
0E
0G
0H
0I
0J
0K
0M
#129000000
b0101 #
1$
1(
b0101 )
10
11
#130000000
b0001 "
b0101 #
0$
b0001 '
0(
b0101 )
1/
00
11
13
#131000000
b0110 #
1$
1(
b0110 )
1+
10
01
12
15
18
19
#132000000
b0010 "
b0110 #
0$
b0010 '
0(
b0110 )
0+
0,
0-
0/
00
01
02
03
05
17
08
19
0:
1;
0=
0@
1A
0B
0E
0H
0I
#133000000
b0111 #
1$
1(
b0111 )
10
11
#134000000
b0011 "
b0111 #
0$
b0011 '
0(
b0111 )
1/
00
11
13
#135000000
b1000 #
1$
1(
b1000 )
1+
1,
1-
10
01
12
15
18
09
1:
1=
1@
0A
1B
1E
1H
1I
#136000000
b0100 "
b1000 #
0$
b0100 '
0(
b1000 )
0+
0,
0/
00
01
02
03
05
07
08
09
0:
0;
0=
1?
0@
0A
0C
1D
0E
#137000000
b1001 #
1$
1(
b1001 )
10
11
#138000000
b0101 "
b1001 #
0$
b0101 '
0(
b1001 )
1/
00
11
13
#139000000
b1010 #
1$
1(
b1010 )
1+
10
01
12
15
18
19
#140000000
b0110 "
b1010 #
0$
b0110 '
0(
b1010 )
0+
0,
0/
00
01
02
03
05
17
08
19
0:
1;
0=
0@
0A
#141000000
b1011 #
1$
1(
b1011 )
10
11
#142000000
b0111 "
b1011 #
0$
b0111 '
0(
b1011 )
1/
00
11
13
#143000000
b1100 #
1$
1(
b1100 )
1+
1,
10
01
12
15
18
09
1:
1=
1@
1A
#144000000
b1000 "
b1100 #
0$
0%
b1000 '
0(
b1100 )
0*
0+
0,
0-
0/
00
01
02
03
05
07
08
09
0:
0;
0=
0?
0@
1A
0B
1C
0D
0E
1G
0H
1I
0J
1K
0M
#145000000
b1101 #
1$
1(
b1101 )
10
11
#146000000
b1001 "
b1101 #
0$
b1001 '
0(
b1101 )
1/
00
11
13
#147000000
b1110 #
1$
1(
b1110 )
1+
10
01
12
15
18
19
#148000000
b1010 "
b1110 #
0$
0%
b1010 '
0(
b1110 )
0*
0+
0,
0-
0/
00
01
02
03
05
17
08
19
0:
1;
0=
0@
1A
0B
0E
0H
1I
0J
0M
#149000000
b1111 #
1$
1(
b1111 )
10
11
#150000000
b1011 "
b1111 #
0$
b1011 '
0(
b1111 )
1/
00
11
13
#151000000
b0000 #
1$
1%
1(
b0000 )
1*
1+
1,
1-
10
01
12
15
18
09
1:
1=
1@
0A
1B
1E
1H
0I
1J
1M
#152000000
b1100 "
b0000 #
0$
b1100 '
0(
b0000 )
0+
0,
0/
00
01
02
03
05
07
08
09
0:
0;
0=
1?
0@
0A
0C
1D
0E
#153000000
b0001 #
1$
1(
b0001 )
10
11
#154000000
b1101 "
b0001 #
0$
b1101 '
0(
b0001 )
1/
00
11
13
#155000000
b0010 #
1$
1(
b0010 )
1+
10
01
12
15
18
19
#156000000
b1110 "
b0010 #
0$
b1110 '
0(
b0010 )
0+
0,
0/
00
01
02
03
05
17
08
19
0:
1;
0=
0@
0A
#157000000
b0011 #
1$
1(
b0011 )
10
11
#158000000
b1111 "
b0011 #
0$
b1111 '
0(
b0011 )
1/
00
11
13
#159000000
b0100 #
1$
1(
b0100 )
1+
1,
10
01
12
15
18
09
1:
1=
1@
1A
#160000000
b0101 !
b0000 "
b0101 #
0$
0%
b0101 &
b0000 '
0(
b0101 )
0*
0+
0,
0-
1.
0/
00
11
02
05
07
08
09
0:
0;
0=
0?
0@
1A
0B
1C
0D
0E
0G
0H
0I
0J
0K
0M
#161000000
b0110 #
1$
1(
b0110 )
1+
10
01
12
15
18
19
#162000000
b0001 "
b0110 #
0$
b0001 '
0(
b0110 )
1/
00
01
03
14
05
#163000000
b0111 #
1$
1(
b0111 )
10
11
#164000000
b0010 "
b0111 #
0$
b0010 '
0(
b0111 )
0+
0,
0-
0/
00
11
02
13
04
17
08
19
0:
1;
0=
0@
1A
0B
0E
0H
0I
#165000000
b1000 #
1$
1(
b1000 )
1+
1,
1-
10
01
12
15
18
09
1:
1=
1@
0A
1B
1E
1H
1I
#166000000
b0011 "
b1000 #
0$
b0011 '
0(
b1000 )
1/
00
01
03
14
05
#167000000
b1001 #
1$
1(
b1001 )
10
11
#168000000
b0100 "
b1001 #
0$
b0100 '
0(
b1001 )
0+
0,
0/
00
11
02
13
04
07
08
09
0:
0;
0=
1?
0@
0A
0C
1D
0E
#169000000
b1010 #
1$
1(
b1010 )
1+
10
01
12
15
18
19
#170000000
b0101 "
b1010 #
0$
b0101 '
0(
b1010 )
1/
00
01
03
14
05
#171000000
b1011 #
1$
1(
b1011 )
10
11
#172000000
b0110 "
b1011 #
0$
b0110 '
0(
b1011 )
0+
0,
0/
00
11
02
13
04
17
08
19
0:
1;
0=
0@
0A
#173000000
b1100 #
1$
1(
b1100 )
1+
1,
10
01
12
15
18
09
1:
1=
1@
1A
#174000000
b0111 "
b1100 #
0$
b0111 '
0(
b1100 )
1/
00
01
03
14
05
#175000000
b1101 #
1$
1(
b1101 )
10
11
#176000000
b1000 "
b1101 #
0$
0%
b1000 '
0(
b1101 )
0*
0+
0,
0-
0/
00
11
02
13
04
07
08
09
0:
0;
0=
0?
0@
1A
0B
1C
0D
0E
1G
0H
1I
0J
1K
0M
#177000000
b1110 #
1$
1(
b1110 )
1+
10
01
12
15
18
19
#178000000
b1001 "
b1110 #
0$
b1001 '
0(
b1110 )
1/
00
01
03
14
05
#179000000
b1111 #
1$
1(
b1111 )
10
11
#180000000
b1010 "
b1111 #
0$
0%
b1010 '
0(
b1111 )
0*
0+
0,
0-
0/
00
11
02
13
04
17
08
19
0:
1;
0=
0@
1A
0B
0E
0H
1I
0J
0M
#181000000
b0000 #
1$
1%
1(
b0000 )
1*
1+
1,
1-
10
01
12
15
18
09
1:
1=
1@
0A
1B
1E
1H
0I
1J
1M
#182000000
b1011 "
b0000 #
0$
b1011 '
0(
b0000 )
1/
00
01
03
14
05
#183000000
b0001 #
1$
1(
b0001 )
10
11
#184000000
b1100 "
b0001 #
0$
b1100 '
0(
b0001 )
0+
0,
0/
00
11
02
13
04
07
08
09
0:
0;
0=
1?
0@
0A
0C
1D
0E
#185000000
b0010 #
1$
1(
b0010 )
1+
10
01
12
15
18
19
#186000000
b1101 "
b0010 #
0$
b1101 '
0(
b0010 )
1/
00
01
03
14
05
#187000000
b0011 #
1$
1(
b0011 )
10
11
#188000000
b1110 "
b0011 #
0$
b1110 '
0(
b0011 )
0+
0,
0/
00
11
02
13
04
17
08
19
0:
1;
0=
0@
0A
#189000000
b0100 #
1$
1(
b0100 )
1+
1,
10
01
12
15
18
09
1:
1=
1@
1A
#190000000
b1111 "
b0100 #
0$
b1111 '
0(
b0100 )
1/
00
01
03
14
05
#191000000
b0101 #
1$
1(
b0101 )
10
11
#192000000
b0110 !
b0000 "
b0110 #
0$
0%
b0110 &
b0000 '
0(
b0110 )
0*
0+
0,
0-
0.
0/
00
01
02
04
16
07
08
19
0:
0=
0?
0@
1A
0B
1C
0D
0E
0G
0H
0I
0J
0K
0M
#193000000
b0111 #
1$
1(
b0111 )
10
11
#194000000
b0001 "
b0111 #
0$
b0001 '
0(
b0111 )
1/
00
11
13
#195000000
b1000 #
1$
1(
b1000 )
1+
1,
1-
10
01
12
15
18
09
1:
1=
1@
0A
1B
1E
1H
1I
#196000000
b0010 "
b1000 #
0$
b0010 '
0(
b1000 )
0+
0/
00
01
02
03
05
17
08
09
0;
1<
0=
#197000000
b1001 #
1$
1(
b1001 )
10
11
#198000000
b0011 "
b1001 #
0$
b0011 '
0(
b1001 )
1/
00
11
13
#199000000
b1010 #
1$
1(
b1010 )
1+
10
01
12
15
18
19
#200000000
b0100 "
b1010 #
0$
b0100 '
0(
b1010 )
0+
0,
0/
00
01
02
03
05
07
08
19
0:
1;
0<
0=
1?
0@
0A
0C
1D
0E
#201000000
b1011 #
1$
1(
b1011 )
10
11
#202000000
b0101 "
b1011 #
0$
b0101 '
0(
b1011 )
1/
00
11
13
#203000000
b1100 #
1$
1(
b1100 )
1+
1,
10
01
12
15
18
09
1:
1=
1@
1A
#204000000
b0110 "
b1100 #
0$
b0110 '
0(
b1100 )
0+
0/
00
01
02
03
05
17
08
09
0;
1<
0=
#205000000
b1101 #
1$
1(
b1101 )
10
11
#206000000
b0111 "
b1101 #
0$
b0111 '
0(
b1101 )
1/
00
11
13
#207000000
b1110 #
1$
1(
b1110 )
1+
10
01
12
15
18
19
#208000000
b1000 "
b1110 #
0$
0%
b1000 '
0(
b1110 )
0*
0+
0,
0-
0/
00
01
02
03
05
07
08
19
0:
1;
0<
0=
0?
0@
1A
0B
1C
0D
0E
1G
0H
1I
0J
1K
0M
#209000000
b1111 #
1$
1(
b1111 )
10
11
#210000000
b1001 "
b1111 #
0$
b1001 '
0(
b1111 )
1/
00
11
13
#211000000
b0000 #
1$
1%
1(
b0000 )
1*
1+
1,
1-
10
01
12
15
18
09
1:
1=
1@
0A
1B
1E
1H
0I
1J
1M
#212000000
b1010 "
b0000 #
0$
b1010 '
0(
b0000 )
0+
0/
00
01
02
03
05
17
08
09
0;
1<
0=
#213000000
b0001 #
1$
1(
b0001 )
10
11
#214000000
b1011 "
b0001 #
0$
b1011 '
0(
b0001 )
1/
00
11
13
#215000000
b0010 #
1$
1(
b0010 )
1+
10
01
12
15
18
19
#216000000
b1100 "
b0010 #
0$
b1100 '
0(
b0010 )
0+
0,
0/
00
01
02
03
05
07
08
19
0:
1;
0<
0=
1?
0@
0A
0C
1D
0E
#217000000
b0011 #
1$
1(
b0011 )
10
11
#218000000
b1101 "
b0011 #
0$
b1101 '
0(
b0011 )
1/
00
11
13
#219000000
b0100 #
1$
1(
b0100 )
1+
1,
10
01
12
15
18
09
1:
1=
1@
1A
#220000000
b1110 "
b0100 #
0$
b1110 '
0(
b0100 )
0+
0/
00
01
02
03
05
17
08
09
0;
1<
0=
#221000000
b0101 #
1$
1(
b0101 )
10
11
#222000000
b1111 "
b0101 #
0$
b1111 '
0(
b0101 )
1/
00
11
13
#223000000
b0110 #
1$
1(
b0110 )
1+
10
01
12
15
18
19
