00_digital_hardware/controller_logic/src/portable_reconstruction/dec_3to8.vhd
-- Portfolio reconstruction from the supplied assignment specification.
-- The original decoder source was referenced by the recovered mux project but
-- was not present in the archive. This file is not presented as recovered work.
library ieee;
use ieee.std_logic_1164.all;

entity dec_3to8 is
  port (
    d2, d1, d0 : in  std_logic;
    y0, y1, y2, y3, y4, y5, y6, y7 : out std_logic
  );
end entity;

architecture rtl of dec_3to8 is
  signal sel : std_logic_vector(2 downto 0);
  signal y   : std_logic_vector(7 downto 0);
begin
  sel <= d2 & d1 & d0;
  with sel select
    y <= "00000001" when "000",
         "00000010" when "001",
         "00000100" when "010",
         "00001000" when "011",
         "00010000" when "100",
         "00100000" when "101",
         "01000000" when "110",
         "10000000" when "111",
         "00000000" when others;
  y0 <= y(0);
  y1 <= y(1);
  y2 <= y(2);
  y3 <= y(3);
  y4 <= y(4);
  y5 <= y(5);
  y6 <= y(6);
  y7 <= y(7);
end architecture;

00_digital_hardware/controller_logic/tb/tb_dec_3to8.vhd
library ieee;
use ieee.std_logic_1164.all;
use ieee.numeric_std.all;
use std.env.all;

entity tb_dec_3to8 is end;
architecture test of tb_dec_3to8 is
  signal d2, d1, d0 : std_logic;
  signal y : std_logic_vector(7 downto 0);
begin
  dut : entity work.dec_3to8
    port map (d2, d1, d0, y(0), y(1), y(2), y(3), y(4), y(5), y(6), y(7));
  process
    variable sel : std_logic_vector(2 downto 0);
  begin
    for i in 0 to 7 loop
      sel := std_logic_vector(to_unsigned(i, 3));
      d2 <= sel(2); d1 <= sel(1); d0 <= sel(0);
      wait for 1 ns;
      assert unsigned(y) = shift_left(to_unsigned(1, 8), i) severity failure;
    end loop;
    report "PASS tb_dec_3to8";
    stop;
    wait;
  end process;
end;

00_digital_hardware/controller_logic/results/vcd/tb_dec_3to8.vcd
$date
  Thu Jul 30 00:29:08 2026
$end
$version
  GHDL v0
$end
$timescale
  1 fs
$end
$scope module standard $end
$upscope $end
$scope module textio $end
$upscope $end
$scope module std_logic_1164 $end
$upscope $end
$scope module numeric_std $end
$upscope $end
$scope module env $end
$upscope $end
$scope module tb_dec_3to8 $end
$var reg 1 ! d2 $end
$var reg 1 " d1 $end
$var reg 1 # d0 $end
$var reg 8 $ y[7:0] $end
$scope module dut $end
$var reg 1 % d2 $end
$var reg 1 & d1 $end
$var reg 1 ' d0 $end
$var reg 1 ( y0 $end
$var reg 1 ) y1 $end
$var reg 1 * y2 $end
$var reg 1 + y3 $end
$var reg 1 , y4 $end
$var reg 1 - y5 $end
$var reg 1 . y6 $end
$var reg 1 / y7 $end
$var reg 3 0 sel[2:0] $end
$var reg 8 1 y[7:0] $end
$upscope $end
$upscope $end
$enddefinitions $end
#0
0!
0"
0#
b00000001 $
0%
0&
0'
1(
0)
0*
0+
0,
0-
0.
0/
b000 0
b00000001 1
#1000000
1#
b00000010 $
1'
0(
1)
b001 0
b00000010 1
#2000000
1"
0#
b00000100 $
1&
0'
0)
1*
b010 0
b00000100 1
#3000000
1#
b00001000 $
1'
0*
1+
b011 0
b00001000 1
#4000000
1!
0"
0#
b00010000 $
1%
0&
0'
0+
1,
b100 0
b00010000 1
#5000000
1#
b00100000 $
1'
0,
1-
b101 0
b00100000 1
#6000000
1"
0#
b01000000 $
1&
0'
0-
1.
b110 0
b01000000 1
#7000000
1#
b10000000 $
1'
0.
1/
b111 0
b10000000 1
