00_digital_hardware/controller_logic/src/original/fulladd.vhd
----------------------------------------------------------------------------------
-- Company: 
-- Engineer: 
-- 
-- Create Date: 2024/10/24 22:24:48
-- Design Name: 
-- Module Name: fulladd - Behavioral
-- Project Name: 
-- Target Devices: 
-- Tool Versions: 
-- Description: 
-- 
-- Dependencies: 
-- 
-- Revision:
-- Revision 0.01 - File Created
-- Additional Comments:
-- 
----------------------------------------------------------------------------------


library IEEE;
use IEEE.STD_LOGIC_1164.ALL;

-- Uncomment the following library declaration if using
-- arithmetic functions with Signed or Unsigned values
--use IEEE.NUMERIC_STD.ALL;

-- Uncomment the following library declaration if instantiating
-- any Xilinx leaf cells in this code.
--library UNISIM;
--use UNISIM.VComponents.all;

entity fulladd is
    Port ( a : in STD_LOGIC;
           b : in STD_LOGIC;
           cin : in STD_LOGIC;
           s : out STD_LOGIC;
           cout : out STD_LOGIC);
end fulladd;

architecture Behavioral of fulladd is
        
        signal t1, t2, t3 : STD_LOGIC ; 
begin

    t1 <= a xor b;
    t2 <= a and b; 
    t3 <= t1 and cin;
    s <= t1 xor cin;
    cout <= t2 or t3; 

end Behavioral;

00_digital_hardware/controller_logic/tb/tb_fulladd.vhd
library ieee;
use ieee.std_logic_1164.all;
use ieee.numeric_std.all;
use std.env.all;

entity tb_fulladd is end;
architecture test of tb_fulladd is
  signal a, b, cin, s, cout : std_logic := '0';
begin
  dut : entity work.fulladd port map (a, b, cin, s, cout);
  process
    variable total : integer;
  begin
    for av in 0 to 1 loop
      for bv in 0 to 1 loop
        for cv in 0 to 1 loop
          a <= std_logic'val(av + 2);
          b <= std_logic'val(bv + 2);
          cin <= std_logic'val(cv + 2);
          wait for 1 ns;
          total := av + bv + cv;
          assert s = std_logic'val((total mod 2) + 2) severity failure;
          assert cout = std_logic'val((total / 2) + 2) severity failure;
        end loop;
      end loop;
    end loop;
    report "PASS tb_fulladd";
    stop;
    wait;
  end process;
end;

00_digital_hardware/controller_logic/results/vcd/tb_fulladd.vcd
$date
  Thu Jul 30 00:29:07 2026
$end
$version
  GHDL v0
$end
$timescale
  1 fs
$end
$scope module standard $end
$upscope $end
$scope module textio $end
$upscope $end
$scope module std_logic_1164 $end
$upscope $end
$scope module numeric_std $end
$upscope $end
$scope module env $end
$upscope $end
$scope module tb_fulladd $end
$var reg 1 ! a $end
$var reg 1 " b $end
$var reg 1 # cin $end
$var reg 1 $ s $end
$var reg 1 % cout $end
$scope module dut $end
$var reg 1 & a $end
$var reg 1 ' b $end
$var reg 1 ( cin $end
$var reg 1 ) s $end
$var reg 1 * cout $end
$var reg 1 + t1 $end
$var reg 1 , t2 $end
$var reg 1 - t3 $end
$upscope $end
$upscope $end
$enddefinitions $end
#0
0!
0"
0#
0$
0%
0&
0'
0(
0)
0*
0+
0,
0-
#1000000
1#
1$
1(
1)
#2000000
1"
0#
1$
1'
0(
1)
1+
#3000000
1#
0$
1%
1(
0)
1*
1-
#4000000
1!
0"
0#
1$
0%
1&
0'
0(
1)
0*
0-
#5000000
1#
0$
1%
1(
0)
1*
1-
#6000000
1"
0#
0$
1'
0(
0)
0+
1,
0-
#7000000
1#
1$
1(
1)
