00_digital_hardware/controller_logic/src/portable_reconstruction/dec_3to8.vhd
-- Portfolio reconstruction from the supplied assignment specification.
-- The original decoder source was referenced by the recovered mux project but
-- was not present in the archive. This file is not presented as recovered work.
library ieee;
use ieee.std_logic_1164.all;

entity dec_3to8 is
  port (
    d2, d1, d0 : in  std_logic;
    y0, y1, y2, y3, y4, y5, y6, y7 : out std_logic
  );
end entity;

architecture rtl of dec_3to8 is
  signal sel : std_logic_vector(2 downto 0);
  signal y   : std_logic_vector(7 downto 0);
begin
  sel <= d2 & d1 & d0;
  with sel select
    y <= "00000001" when "000",
         "00000010" when "001",
         "00000100" when "010",
         "00001000" when "011",
         "00010000" when "100",
         "00100000" when "101",
         "01000000" when "110",
         "10000000" when "111",
         "00000000" when others;
  y0 <= y(0);
  y1 <= y(1);
  y2 <= y(2);
  y3 <= y(3);
  y4 <= y(4);
  y5 <= y(5);
  y6 <= y(6);
  y7 <= y(7);
end architecture;

00_digital_hardware/controller_logic/src/original/mux_8to1.vhd
----------------------------------------------------------------------------------
-- Company: 
-- Engineer: 
-- 
-- Create Date: 2024/11/07 22:13:53
-- Design Name: 
-- Module Name: mux_8to1 - Behavioral
-- Project Name: 
-- Target Devices: 
-- Tool Versions: 
-- Description: 
-- 
-- Dependencies: 
-- 
-- Revision:
-- Revision 0.01 - File Created
-- Additional Comments:
-- 
----------------------------------------------------------------------------------


library IEEE;
use IEEE.STD_LOGIC_1164.ALL;

-- Uncomment the following library declaration if using
-- arithmetic functions with Signed or Unsigned values
--use IEEE.NUMERIC_STD.ALL;

-- Uncomment the following library declaration if instantiating
-- any Xilinx leaf cells in this code.
--library UNISIM;
--use UNISIM.VComponents.all;

entity mux_8to1 is 
    Port ( a : in STD_LOGIC;
           b : in STD_LOGIC;
           c : in STD_LOGIC;
           d : in STD_LOGIC;
           e : in STD_LOGIC;
           f : in STD_LOGIC;
           g : in STD_LOGIC;
           h : in STD_LOGIC;
           s2 : in STD_LOGIC;
           s1 : in STD_LOGIC;
           s0 : in STD_LOGIC;
           y : out STD_LOGIC);
end mux_8to1;

architecture Behavioral of mux_8to1 is
    component dec_3to8 is
        Port ( d2, d1, d0 : in STD_LOGIC;
               y0, y1, y2, y3, y4, y5, y6, y7 : out STD_LOGIC);
    end component;
    
    signal d0, d1, d2, d3, d4, d5, d6, d7 : std_logic;
    signal t0, t1, t2, t3, t4, t5, t6, t7 : std_logic;

begin
    U1: dec_3to8 port map (d2 => s2, d1 => s1, d0 => s0, 
                          y0 => d0, y1 => d1, y2 => d2, 
                          y3 => d3, y4 => d4, y5 => d5, 
                          y6 => d6, y7 => d7);
       
    t0 <= a and d0;
    t1 <= b and d1;
    t2 <= c and d2;
    t3 <= d and d3;
    t4 <= e and d4;
    t5 <= f and d5;       
    t6 <= g and d6;
    t7 <= h and d7;
    
    y <= t0 or t1 or t2 or t3 or t4 or t5 or t6 or t7;
end Behavioral;

00_digital_hardware/controller_logic/tb/tb_mux_8to1.vhd
library ieee;
use ieee.std_logic_1164.all;
use ieee.numeric_std.all;
use std.env.all;

entity tb_mux_8to1 is end;
architecture test of tb_mux_8to1 is
  signal a,b,c,d,e,f,g,h,s2,s1,s0,y : std_logic;
  constant data : std_logic_vector(7 downto 0) := "01001101";
begin
  dut : entity work.mux_8to1 port map (a,b,c,d,e,f,g,h,s2,s1,s0,y);
  a <= data(0); b <= data(1); c <= data(2); d <= data(3);
  e <= data(4); f <= data(5); g <= data(6); h <= data(7);
  process
    variable sel : std_logic_vector(2 downto 0);
  begin
    for i in 0 to 7 loop
      sel := std_logic_vector(to_unsigned(i,3));
      s2 <= sel(2); s1 <= sel(1); s0 <= sel(0);
      wait for 1 ns;
      assert y = data(i) severity failure;
    end loop;
    report "PASS tb_mux_8to1";
    stop;
    wait;
  end process;
end;

00_digital_hardware/controller_logic/results/vcd/tb_mux_8to1.vcd
$date
  Thu Jul 30 00:29:08 2026
$end
$version
  GHDL v0
$end
$timescale
  1 fs
$end
$scope module standard $end
$upscope $end
$scope module textio $end
$upscope $end
$scope module std_logic_1164 $end
$upscope $end
$scope module numeric_std $end
$upscope $end
$scope module env $end
$upscope $end
$scope module tb_mux_8to1 $end
$var reg 1 ! a $end
$var reg 1 " b $end
$var reg 1 # c $end
$var reg 1 $ d $end
$var reg 1 % e $end
$var reg 1 & f $end
$var reg 1 ' g $end
$var reg 1 ( h $end
$var reg 1 ) s2 $end
$var reg 1 * s1 $end
$var reg 1 + s0 $end
$var reg 1 , y $end
$scope module dut $end
$var reg 1 - a $end
$var reg 1 . b $end
$var reg 1 / c $end
$var reg 1 0 d $end
$var reg 1 1 e $end
$var reg 1 2 f $end
$var reg 1 3 g $end
$var reg 1 4 h $end
$var reg 1 5 s2 $end
$var reg 1 6 s1 $end
$var reg 1 7 s0 $end
$var reg 1 8 y $end
$var reg 1 9 d0 $end
$var reg 1 : d1 $end
$var reg 1 ; d2 $end
$var reg 1 < d3 $end
$var reg 1 = d4 $end
$var reg 1 > d5 $end
$var reg 1 ? d6 $end
$var reg 1 @ d7 $end
$var reg 1 A t0 $end
$var reg 1 B t1 $end
$var reg 1 C t2 $end
$var reg 1 D t3 $end
$var reg 1 E t4 $end
$var reg 1 F t5 $end
$var reg 1 G t6 $end
$var reg 1 H t7 $end
$scope module u1 $end
$var reg 1 I d2 $end
$var reg 1 J d1 $end
$var reg 1 K d0 $end
$var reg 1 L y0 $end
$var reg 1 M y1 $end
$var reg 1 N y2 $end
$var reg 1 O y3 $end
$var reg 1 P y4 $end
$var reg 1 Q y5 $end
$var reg 1 R y6 $end
$var reg 1 S y7 $end
$var reg 3 T sel[2:0] $end
$var reg 8 U y[7:0] $end
$upscope $end
$upscope $end
$upscope $end
$enddefinitions $end
#0
1!
0"
1#
1$
0%
0&
1'
0(
0)
0*
0+
1,
1-
0.
1/
10
01
02
13
04
05
06
07
18
19
0:
0;
0<
0=
0>
0?
0@
1A
0B
0C
0D
0E
0F
0G
0H
0I
0J
0K
1L
0M
0N
0O
0P
0Q
0R
0S
b000 T
b00000001 U
#1000000
1+
0,
17
08
09
1:
0A
1K
0L
1M
b001 T
b00000010 U
#2000000
1*
0+
1,
16
07
18
0:
1;
1C
1J
0K
0M
1N
b010 T
b00000100 U
#3000000
1+
17
0;
1<
0C
1D
1K
0N
1O
b011 T
b00001000 U
#4000000
1)
0*
0+
0,
15
06
07
08
0<
1=
0D
1I
0J
0K
0O
1P
b100 T
b00010000 U
#5000000
1+
17
0=
1>
1K
0P
1Q
b101 T
b00100000 U
#6000000
1*
0+
1,
16
07
18
0>
1?
1G
1J
0K
0Q
1R
b110 T
b01000000 U
#7000000
1+
0,
17
08
0?
1@
0G
1K
0R
1S
b111 T
b10000000 U
