00_digital_hardware/controller_logic/src/original/mealy_101.vhd
----------------------------------------------------------------------------------
-- Company: 
-- Engineer: 
-- 
-- Create Date: 2024/11/22 16:00:10
-- Design Name: 
-- Module Name: mealy - Behavioral
-- Project Name: 
-- Target Devices: 
-- Tool Versions: 
-- Description: 
-- 
-- Dependencies: 
-- 
-- Revision:
-- Revision 0.01 - File Created
-- Additional Comments:
-- 
----------------------------------------------------------------------------------


library IEEE;
use IEEE.STD_LOGIC_1164.ALL;

-- Uncomment the following library declaration if using
-- arithmetic functions with Signed or Unsigned values
--use IEEE.NUMERIC_STD.ALL;

-- Uncomment the following library declaration if instantiating
-- any Xilinx leaf cells in this code.
--library UNISIM;
--use UNISIM.VComponents.all;

entity mealy is
    Port ( clk : in STD_LOGIC;
           din : in STD_LOGIC;
           rst : in STD_LOGIC;
           dout : out STD_LOGIC);
end mealy;

architecture Behavioral of mealy is
    type state is (st0, st1, st2, st3);
    signal present_state, next_state : state;
begin
    syncronous_process : process (clk)
    begin
        if rising_edge(clk) then
            if (rst = '1') then
                present_state <= st0;
            else
                present_state <= next_state;
            end if;
        end if;
    end process;
    
    next_state_and_output_decoder :       
    process(present_state, din)
    begin
        case (present_state) is 
            when st0 =>
                     if (din = '1') then
                            next_state <= st1;
                            dout <= '0';
                    else
                            next_state <= st0;
                            dout <= '0';
                    end if;
            
            when St1 =>
                   if (din = '0') then
                            next_state <= st2;
                            dout <= '0';
                   else
                            next_state <= st1;
                            dout <= '0';
                   end if;
            
            when St2 =>
                   if (din = '1') then
                            next_state <= st1;
                            dout <= '1';
                   else
                            next_state <= st2;
                            dout <= '0';
                   end if;            
            
            when others =>
                   next_state <= st0;
                   dout <= '0';
        end case;
    end process;
end Behavioral;

00_digital_hardware/controller_logic/tb/tb_mealy_101.vhd
library ieee;
use ieee.std_logic_1164.all;
use std.env.all;

entity tb_mealy_101 is end;
architecture test of tb_mealy_101 is
  signal clk : std_logic := '0';
  signal rst : std_logic := '1';
  signal din, dout : std_logic := '0';
  type bit_array is array (natural range <>) of std_logic;
  constant stimulus : bit_array := ('1','0','1','0','1');
  constant expected : bit_array := ('0','0','1','0','1');
begin
  clk <= not clk after 5 ns;
  dut : entity work.mealy port map (clk, din, rst, dout);
  process
  begin
    wait until rising_edge(clk);
    rst <= '0';
    for i in stimulus'range loop
      wait until falling_edge(clk);
      din <= stimulus(i);
      wait for 1 ns;
      assert dout = expected(i) severity failure;
    end loop;
    report "PASS tb_mealy_101";
    stop;
    wait;
  end process;
end;

00_digital_hardware/controller_logic/results/vcd/tb_mealy_101.vcd
$date
  Thu Jul 30 00:29:08 2026
$end
$version
  GHDL v0
$end
$timescale
  1 fs
$end
$scope module standard $end
$upscope $end
$scope module textio $end
$upscope $end
$scope module std_logic_1164 $end
$upscope $end
$scope module env $end
$upscope $end
$scope module tb_mealy_101 $end
$var reg 1 ! clk $end
$var reg 1 " rst $end
$var reg 1 # din $end
$var reg 1 $ dout $end
$scope module dut $end
$var reg 1 % clk $end
$var reg 1 & din $end
$var reg 1 ' rst $end
$var reg 1 ( dout $end
$comment present_state is not handled $end
$comment next_state is not handled $end
$upscope $end
$upscope $end
$enddefinitions $end
#0
0!
1"
0#
0$
0%
0&
1'
0(
#5000000
1!
0"
1%
0'
#10000000
0!
1#
0%
1&
#15000000
1!
1%
#20000000
0!
0#
0%
0&
#25000000
1!
1%
#30000000
0!
1#
1$
0%
1&
1(
#35000000
1!
0$
1%
0(
#40000000
0!
0#
0%
0&
#45000000
1!
1%
#50000000
0!
1#
1$
0%
1&
1(
