00_digital_hardware/controller_logic/src/portable_reconstruction/dec_3to8.vhd
-- Portfolio reconstruction from the supplied assignment specification.
-- The original decoder source was referenced by the recovered mux project but
-- was not present in the archive. This file is not presented as recovered work.
library ieee;
use ieee.std_logic_1164.all;

entity dec_3to8 is
  port (
    d2, d1, d0 : in  std_logic;
    y0, y1, y2, y3, y4, y5, y6, y7 : out std_logic
  );
end entity;

architecture rtl of dec_3to8 is
  signal sel : std_logic_vector(2 downto 0);
  signal y   : std_logic_vector(7 downto 0);
begin
  sel <= d2 & d1 & d0;
  with sel select
    y <= "00000001" when "000",
         "00000010" when "001",
         "00000100" when "010",
         "00001000" when "011",
         "00010000" when "100",
         "00100000" when "101",
         "01000000" when "110",
         "10000000" when "111",
         "00000000" when others;
  y0 <= y(0);
  y1 <= y(1);
  y2 <= y(2);
  y3 <= y(3);
  y4 <= y(4);
  y5 <= y(5);
  y6 <= y(6);
  y7 <= y(7);
end architecture;

00_digital_hardware/controller_logic/src/original/mux_8to1.vhd
----------------------------------------------------------------------------------
-- Company: 
-- Engineer: 
-- 
-- Create Date: 2024/11/07 22:13:53
-- Design Name: 
-- Module Name: mux_8to1 - Behavioral
-- Project Name: 
-- Target Devices: 
-- Tool Versions: 
-- Description: 
-- 
-- Dependencies: 
-- 
-- Revision:
-- Revision 0.01 - File Created
-- Additional Comments:
-- 
----------------------------------------------------------------------------------


library IEEE;
use IEEE.STD_LOGIC_1164.ALL;

-- Uncomment the following library declaration if using
-- arithmetic functions with Signed or Unsigned values
--use IEEE.NUMERIC_STD.ALL;

-- Uncomment the following library declaration if instantiating
-- any Xilinx leaf cells in this code.
--library UNISIM;
--use UNISIM.VComponents.all;

entity mux_8to1 is 
    Port ( a : in STD_LOGIC;
           b : in STD_LOGIC;
           c : in STD_LOGIC;
           d : in STD_LOGIC;
           e : in STD_LOGIC;
           f : in STD_LOGIC;
           g : in STD_LOGIC;
           h : in STD_LOGIC;
           s2 : in STD_LOGIC;
           s1 : in STD_LOGIC;
           s0 : in STD_LOGIC;
           y : out STD_LOGIC);
end mux_8to1;

architecture Behavioral of mux_8to1 is
    component dec_3to8 is
        Port ( d2, d1, d0 : in STD_LOGIC;
               y0, y1, y2, y3, y4, y5, y6, y7 : out STD_LOGIC);
    end component;
    
    signal d0, d1, d2, d3, d4, d5, d6, d7 : std_logic;
    signal t0, t1, t2, t3, t4, t5, t6, t7 : std_logic;

begin
    U1: dec_3to8 port map (d2 => s2, d1 => s1, d0 => s0, 
                          y0 => d0, y1 => d1, y2 => d2, 
                          y3 => d3, y4 => d4, y5 => d5, 
                          y6 => d6, y7 => d7);
       
    t0 <= a and d0;
    t1 <= b and d1;
    t2 <= c and d2;
    t3 <= d and d3;
    t4 <= e and d4;
    t5 <= f and d5;       
    t6 <= g and d6;
    t7 <= h and d7;
    
    y <= t0 or t1 or t2 or t3 or t4 or t5 or t6 or t7;
end Behavioral;

00_digital_hardware/controller_logic/src/portable_reconstruction/mux_8to1_4bits.vhd
-- Portfolio reconstruction from the supplied assignment specification.
library ieee;
use ieee.std_logic_1164.all;

entity mux_8to1_4bits is
  port (
    a, b, c, d, e, f, g, h : in  std_logic_vector(3 downto 0);
    s2, s1, s0             : in  std_logic;
    y                       : out std_logic_vector(3 downto 0)
  );
end entity;

architecture structural of mux_8to1_4bits is
  component mux_8to1 is
    port (
      a, b, c, d, e, f, g, h : in std_logic;
      s2, s1, s0 : in std_logic;
      y : out std_logic
    );
  end component;
begin
  gen_bits : for i in 0 to 3 generate
    u_mux : mux_8to1
      port map (
        a => a(i), b => b(i), c => c(i), d => d(i),
        e => e(i), f => f(i), g => g(i), h => h(i),
        s2 => s2, s1 => s1, s0 => s0, y => y(i)
      );
  end generate;
end architecture;

00_digital_hardware/controller_logic/tb/tb_mux_8to1_4bits.vhd
library ieee;
use ieee.std_logic_1164.all;
use ieee.numeric_std.all;
use std.env.all;

entity tb_mux_8to1_4bits is end;
architecture test of tb_mux_8to1_4bits is
  signal a,b,c,d,e,f,g,h,y : std_logic_vector(3 downto 0);
  signal s2,s1,s0 : std_logic;
begin
  dut : entity work.mux_8to1_4bits port map (a,b,c,d,e,f,g,h,s2,s1,s0,y);
  a<="0000"; b<="0001"; c<="0010"; d<="0011";
  e<="0100"; f<="0101"; g<="0110"; h<="0111";
  process
    variable sel : std_logic_vector(2 downto 0);
  begin
    for i in 0 to 7 loop
      sel := std_logic_vector(to_unsigned(i,3));
      s2 <= sel(2); s1 <= sel(1); s0 <= sel(0);
      wait for 1 ns;
      assert unsigned(y) = to_unsigned(i,4) severity failure;
    end loop;
    report "PASS tb_mux_8to1_4bits";
    stop;
    wait;
  end process;
end;

00_digital_hardware/controller_logic/results/vcd/tb_mux_8to1_4bits.vcd
$date
  Thu Jul 30 00:29:08 2026
$end
$version
  GHDL v0
$end
$timescale
  1 fs
$end
$scope module standard $end
$upscope $end
$scope module textio $end
$upscope $end
$scope module std_logic_1164 $end
$upscope $end
$scope module numeric_std $end
$upscope $end
$scope module env $end
$upscope $end
$scope module tb_mux_8to1_4bits $end
$var reg 4 ! a[3:0] $end
$var reg 4 " b[3:0] $end
$var reg 4 # c[3:0] $end
$var reg 4 $ d[3:0] $end
$var reg 4 % e[3:0] $end
$var reg 4 & f[3:0] $end
$var reg 4 ' g[3:0] $end
$var reg 4 ( h[3:0] $end
$var reg 4 ) y[3:0] $end
$var reg 1 * s2 $end
$var reg 1 + s1 $end
$var reg 1 , s0 $end
$scope module dut $end
$var reg 4 - a[3:0] $end
$var reg 4 . b[3:0] $end
$var reg 4 / c[3:0] $end
$var reg 4 0 d[3:0] $end
$var reg 4 1 e[3:0] $end
$var reg 4 2 f[3:0] $end
$var reg 4 3 g[3:0] $end
$var reg 4 4 h[3:0] $end
$var reg 1 5 s2 $end
$var reg 1 6 s1 $end
$var reg 1 7 s0 $end
$var reg 4 8 y[3:0] $end
$scope module gen_bits(0) $end
$scope module u_mux $end
$var reg 1 9 a $end
$var reg 1 : b $end
$var reg 1 ; c $end
$var reg 1 < d $end
$var reg 1 = e $end
$var reg 1 > f $end
$var reg 1 ? g $end
$var reg 1 @ h $end
$var reg 1 A s2 $end
$var reg 1 B s1 $end
$var reg 1 C s0 $end
$var reg 1 D y $end
$var reg 1 E d0 $end
$var reg 1 F d1 $end
$var reg 1 G d2 $end
$var reg 1 H d3 $end
$var reg 1 I d4 $end
$var reg 1 J d5 $end
$var reg 1 K d6 $end
$var reg 1 L d7 $end
$var reg 1 M t0 $end
$var reg 1 N t1 $end
$var reg 1 O t2 $end
$var reg 1 P t3 $end
$var reg 1 Q t4 $end
$var reg 1 R t5 $end
$var reg 1 S t6 $end
$var reg 1 T t7 $end
$scope module u1 $end
$var reg 1 U d2 $end
$var reg 1 V d1 $end
$var reg 1 W d0 $end
$var reg 1 X y0 $end
$var reg 1 Y y1 $end
$var reg 1 Z y2 $end
$var reg 1 [ y3 $end
$var reg 1 \ y4 $end
$var reg 1 ] y5 $end
$var reg 1 ^ y6 $end
$var reg 1 _ y7 $end
$var reg 3 ` sel[2:0] $end
$var reg 8 a y[7:0] $end
$upscope $end
$upscope $end
$upscope $end
$scope module gen_bits(1) $end
$scope module u_mux $end
$var reg 1 b a $end
$var reg 1 c b $end
$var reg 1 d c $end
$var reg 1 e d $end
$var reg 1 f e $end
$var reg 1 g f $end
$var reg 1 h g $end
$var reg 1 i h $end
$var reg 1 j s2 $end
$var reg 1 k s1 $end
$var reg 1 l s0 $end
$var reg 1 m y $end
$var reg 1 n d0 $end
$var reg 1 o d1 $end
$var reg 1 p d2 $end
$var reg 1 q d3 $end
$var reg 1 r d4 $end
$var reg 1 s d5 $end
$var reg 1 t d6 $end
$var reg 1 u d7 $end
$var reg 1 v t0 $end
$var reg 1 w t1 $end
$var reg 1 x t2 $end
$var reg 1 y t3 $end
$var reg 1 z t4 $end
$var reg 1 { t5 $end
$var reg 1 | t6 $end
$var reg 1 } t7 $end
$scope module u1 $end
$var reg 1 !" d2 $end
$var reg 1 "" d1 $end
$var reg 1 #" d0 $end
$var reg 1 $" y0 $end
$var reg 1 %" y1 $end
$var reg 1 &" y2 $end
$var reg 1 '" y3 $end
$var reg 1 (" y4 $end
$var reg 1 )" y5 $end
$var reg 1 *" y6 $end
$var reg 1 +" y7 $end
$var reg 3 ," sel[2:0] $end
$var reg 8 -" y[7:0] $end
$upscope $end
$upscope $end
$upscope $end
$scope module gen_bits(2) $end
$scope module u_mux $end
$var reg 1 ." a $end
$var reg 1 /" b $end
$var reg 1 0" c $end
$var reg 1 1" d $end
$var reg 1 2" e $end
$var reg 1 3" f $end
$var reg 1 4" g $end
$var reg 1 5" h $end
$var reg 1 6" s2 $end
$var reg 1 7" s1 $end
$var reg 1 8" s0 $end
$var reg 1 9" y $end
$var reg 1 :" d0 $end
$var reg 1 ;" d1 $end
$var reg 1 <" d2 $end
$var reg 1 =" d3 $end
$var reg 1 >" d4 $end
$var reg 1 ?" d5 $end
$var reg 1 @" d6 $end
$var reg 1 A" d7 $end
$var reg 1 B" t0 $end
$var reg 1 C" t1 $end
$var reg 1 D" t2 $end
$var reg 1 E" t3 $end
$var reg 1 F" t4 $end
$var reg 1 G" t5 $end
$var reg 1 H" t6 $end
$var reg 1 I" t7 $end
$scope module u1 $end
$var reg 1 J" d2 $end
$var reg 1 K" d1 $end
$var reg 1 L" d0 $end
$var reg 1 M" y0 $end
$var reg 1 N" y1 $end
$var reg 1 O" y2 $end
$var reg 1 P" y3 $end
$var reg 1 Q" y4 $end
$var reg 1 R" y5 $end
$var reg 1 S" y6 $end
$var reg 1 T" y7 $end
$var reg 3 U" sel[2:0] $end
$var reg 8 V" y[7:0] $end
$upscope $end
$upscope $end
$upscope $end
$scope module gen_bits(3) $end
$scope module u_mux $end
$var reg 1 W" a $end
$var reg 1 X" b $end
$var reg 1 Y" c $end
$var reg 1 Z" d $end
$var reg 1 [" e $end
$var reg 1 \" f $end
$var reg 1 ]" g $end
$var reg 1 ^" h $end
$var reg 1 _" s2 $end
$var reg 1 `" s1 $end
$var reg 1 a" s0 $end
$var reg 1 b" y $end
$var reg 1 c" d0 $end
$var reg 1 d" d1 $end
$var reg 1 e" d2 $end
$var reg 1 f" d3 $end
$var reg 1 g" d4 $end
$var reg 1 h" d5 $end
$var reg 1 i" d6 $end
$var reg 1 j" d7 $end
$var reg 1 k" t0 $end
$var reg 1 l" t1 $end
$var reg 1 m" t2 $end
$var reg 1 n" t3 $end
$var reg 1 o" t4 $end
$var reg 1 p" t5 $end
$var reg 1 q" t6 $end
$var reg 1 r" t7 $end
$scope module u1 $end
$var reg 1 s" d2 $end
$var reg 1 t" d1 $end
$var reg 1 u" d0 $end
$var reg 1 v" y0 $end
$var reg 1 w" y1 $end
$var reg 1 x" y2 $end
$var reg 1 y" y3 $end
$var reg 1 z" y4 $end
$var reg 1 {" y5 $end
$var reg 1 |" y6 $end
$var reg 1 }" y7 $end
$var reg 3 !# sel[2:0] $end
$var reg 8 "# y[7:0] $end
$upscope $end
$upscope $end
$upscope $end
$upscope $end
$upscope $end
$enddefinitions $end
#0
b0000 !
b0001 "
b0010 #
b0011 $
b0100 %
b0101 &
b0110 '
b0111 (
b0000 )
0*
0+
0,
b0000 -
b0001 .
b0010 /
b0011 0
b0100 1
b0101 2
b0110 3
b0111 4
05
06
07
b0000 8
09
1:
0;
1<
0=
1>
0?
1@
0A
0B
0C
0D
1E
0F
0G
0H
0I
0J
0K
0L
0M
0N
0O
0P
0Q
0R
0S
0T
0U
0V
0W
1X
0Y
0Z
0[
0\
0]
0^
0_
b000 `
b00000001 a
0b
0c
1d
1e
0f
0g
1h
1i
0j
0k
0l
0m
1n
0o
0p
0q
0r
0s
0t
0u
0v
0w
0x
0y
0z
0{
0|
0}
0!"
0""
0#"
1$"
0%"
0&"
0'"
0("
0)"
0*"
0+"
b000 ,"
b00000001 -"
0."
0/"
00"
01"
12"
13"
14"
15"
06"
07"
08"
09"
1:"
0;"
0<"
0="
0>"
0?"
0@"
0A"
0B"
0C"
0D"
0E"
0F"
0G"
0H"
0I"
0J"
0K"
0L"
1M"
0N"
0O"
0P"
0Q"
0R"
0S"
0T"
b000 U"
b00000001 V"
0W"
0X"
0Y"
0Z"
0["
0\"
0]"
0^"
0_"
0`"
0a"
0b"
1c"
0d"
0e"
0f"
0g"
0h"
0i"
0j"
0k"
0l"
0m"
0n"
0o"
0p"
0q"
0r"
0s"
0t"
0u"
1v"
0w"
0x"
0y"
0z"
0{"
0|"
0}"
b000 !#
b00000001 "#
#1000000
b0001 )
1,
17
b0001 8
1C
1D
0E
1F
1N
1W
0X
1Y
b001 `
b00000010 a
1l
0n
1o
1#"
0$"
1%"
b001 ,"
b00000010 -"
18"
0:"
1;"
1L"
0M"
1N"
b001 U"
b00000010 V"
1a"
0c"
1d"
1u"
0v"
1w"
b001 !#
b00000010 "#
#2000000
b0010 )
1+
0,
16
07
b0010 8
1B
0C
0D
0F
1G
0N
1V
0W
0Y
1Z
b010 `
b00000100 a
1k
0l
1m
0o
1p
1x
1""
0#"
0%"
1&"
b010 ,"
b00000100 -"
17"
08"
0;"
1<"
1K"
0L"
0N"
1O"
b010 U"
b00000100 V"
1`"
0a"
0d"
1e"
1t"
0u"
0w"
1x"
b010 !#
b00000100 "#
#3000000
b0011 )
1,
17
b0011 8
1C
1D
0G
1H
1P
1W
0Z
1[
b011 `
b00001000 a
1l
0p
1q
0x
1y
1#"
0&"
1'"
b011 ,"
b00001000 -"
18"
0<"
1="
1L"
0O"
1P"
b011 U"
b00001000 V"
1a"
0e"
1f"
1u"
0x"
1y"
b011 !#
b00001000 "#
#4000000
b0100 )
1*
0+
0,
15
06
07
b0100 8
1A
0B
0C
0D
0H
1I
0P
1U
0V
0W
0[
1\
b100 `
b00010000 a
1j
0k
0l
0m
0q
1r
0y
1!"
0""
0#"
0'"
1("
b100 ,"
b00010000 -"
16"
07"
08"
19"
0="
1>"
1F"
1J"
0K"
0L"
0P"
1Q"
b100 U"
b00010000 V"
1_"
0`"
0a"
0f"
1g"
1s"
0t"
0u"
0y"
1z"
b100 !#
b00010000 "#
#5000000
b0101 )
1,
17
b0101 8
1C
1D
0I
1J
1R
1W
0\
1]
b101 `
b00100000 a
1l
0r
1s
1#"
0("
1)"
b101 ,"
b00100000 -"
18"
0>"
1?"
0F"
1G"
1L"
0Q"
1R"
b101 U"
b00100000 V"
1a"
0g"
1h"
1u"
0z"
1{"
b101 !#
b00100000 "#
#6000000
b0110 )
1+
0,
16
07
b0110 8
1B
0C
0D
0J
1K
0R
1V
0W
0]
1^
b110 `
b01000000 a
1k
0l
1m
0s
1t
1|
1""
0#"
0)"
1*"
b110 ,"
b01000000 -"
17"
08"
0?"
1@"
0G"
1H"
1K"
0L"
0R"
1S"
b110 U"
b01000000 V"
1`"
0a"
0h"
1i"
1t"
0u"
0{"
1|"
b110 !#
b01000000 "#
#7000000
b0111 )
1,
17
b0111 8
1C
1D
0K
1L
1T
1W
0^
1_
b111 `
b10000000 a
1l
0t
1u
0|
1}
1#"
0*"
1+"
b111 ,"
b10000000 -"
18"
0@"
1A"
0H"
1I"
1L"
0S"
1T"
b111 U"
b10000000 V"
1a"
0i"
1j"
1u"
0|"
1}"
b111 !#
b10000000 "#
