00_digital_hardware/controller_logic/src/portable_reconstruction/usr_4bit.vhd
-- Portfolio reconstruction from the supplied assignment specification.
-- The recovered material documented behavior and an archived waveform, but the
-- completed source was not present. Clear is implemented asynchronously here
-- and this assumption is explicitly excluded from claims about the old archive.
library ieee;
use ieee.std_logic_1164.all;

entity usr_4bit is
  port (
    clk, clear : in  std_logic;
    s          : in  std_logic_vector(1 downto 0);
    d_in       : in  std_logic;
    p_in       : in  std_logic_vector(3 downto 0);
    q          : out std_logic_vector(3 downto 0)
  );
end entity;

architecture rtl of usr_4bit is
  signal q_reg : std_logic_vector(3 downto 0) := "0001";
begin
  process (clk, clear)
  begin
    if clear = '1' then
      q_reg <= (others => '0');
    elsif rising_edge(clk) then
      case s is
        when "00" => q_reg <= q_reg;
        when "01" => q_reg <= d_in & q_reg(3 downto 1);
        when "10" => q_reg <= q_reg(2 downto 0) & d_in;
        when "11" => q_reg <= p_in;
        when others => q_reg <= q_reg;
      end case;
    end if;
  end process;
  q <= q_reg;
end architecture;

00_digital_hardware/controller_logic/tb/tb_usr_4bit.vhd
library ieee;
use ieee.std_logic_1164.all;
use std.env.all;

entity tb_usr_4bit is end;
architecture test of tb_usr_4bit is
  signal clk : std_logic := '0';
  signal clear, d_in : std_logic := '0';
  signal s : std_logic_vector(1 downto 0) := "00";
  signal p_in, q : std_logic_vector(3 downto 0) := (others => '0');
begin
  clk <= not clk after 5 ns;
  dut : entity work.usr_4bit port map (clk, clear, s, d_in, p_in, q);
  process
  begin
    clear <= '1'; wait for 2 ns; assert q = "0000" severity failure;
    clear <= '0'; p_in <= "1010"; s <= "11";
    wait until rising_edge(clk); wait for 1 ns; assert q = "1010" severity failure;
    d_in <= '1'; s <= "01";
    wait until rising_edge(clk); wait for 1 ns; assert q = "1101" severity failure;
    d_in <= '0'; s <= "10";
    wait until rising_edge(clk); wait for 1 ns; assert q = "1010" severity failure;
    s <= "00";
    wait until rising_edge(clk); wait for 1 ns; assert q = "1010" severity failure;
    report "PASS tb_usr_4bit";
    stop;
    wait;
  end process;
end;

00_digital_hardware/controller_logic/results/vcd/tb_usr_4bit.vcd
$date
  Thu Jul 30 00:29:08 2026
$end
$version
  GHDL v0
$end
$timescale
  1 fs
$end
$scope module standard $end
$upscope $end
$scope module textio $end
$upscope $end
$scope module std_logic_1164 $end
$upscope $end
$scope module env $end
$upscope $end
$scope module tb_usr_4bit $end
$var reg 1 ! clk $end
$var reg 1 " clear $end
$var reg 1 # d_in $end
$var reg 2 $ s[1:0] $end
$var reg 4 % p_in[3:0] $end
$var reg 4 & q[3:0] $end
$scope module dut $end
$var reg 1 ' clk $end
$var reg 1 ( clear $end
$var reg 2 ) s[1:0] $end
$var reg 1 * d_in $end
$var reg 4 + p_in[3:0] $end
$var reg 4 , q[3:0] $end
$var reg 4 - q_reg[3:0] $end
$upscope $end
$upscope $end
$enddefinitions $end
#0
0!
1"
0#
b00 $
b0000 %
b0000 &
0'
1(
b00 )
0*
b0000 +
b0000 ,
b0000 -
#2000000
0"
b11 $
b1010 %
0(
b11 )
b1010 +
#5000000
1!
b1010 &
1'
b1010 ,
b1010 -
#6000000
1#
b01 $
b01 )
1*
#10000000
0!
0'
#15000000
1!
b1101 &
1'
b1101 ,
b1101 -
#16000000
0#
b10 $
b10 )
0*
#20000000
0!
0'
#25000000
1!
b1010 &
1'
b1010 ,
b1010 -
#26000000
b00 $
b00 )
